[
    {
        "label":"Doctorate",
        "value":"Doctorate"

    },
    {
        "label":"Master's or professional degree",
        "value":"Master's or professional degree"

    },
    {
        "label":"Bachelor's degree",
        "value":"Bachelor's degree"

    },
    {
        "label":"Associate degree",
        "value":"Associate degree"

    },
    {
        "label":"Secondary/high school",
        "value":"Secondary/high school"

    },
    {
        "label":"Junior secondary/junior high/middle school",
        "value":"Junior secondary/junior high/middle school"

    },
    {
        "label":"Elementary/primary school",
        "value":"Elementary/primary school"

    },
    {
        "label":"No formal education",
        "value":"No formal education"

    },
    {
        "label":"Other education",
        "value":"Other education"
    }
]
